{"Camera":{"SysTime": "20140827_213540297", "Parameter": {"focus_mode" : "continuous-video", "width":"1280", "height": "720"}, "File": "/sdcard/8월/2014/08/27/21/RGB/TEGRA7_RGB_20140827_213540297.jpg" },"Tracking":{"SysTime": "20140827_213540297", "X": "564", "Y": "404", "W": "160", "H": "60", "File": "/sdcard/8월/2014/08/27/21/TRACKING/TEGRA7_TRACKING_20140827_213540297.jpg" },"GPS":{"UtcTime": "1409142923000", "Latitude": "37.963094101287425", "Longitude": "126.86766137368977", "Speed": "4.4531164", "Altitude": "84.0", "Accuracy": "3.9199626" },"Attitude":{"SysTime": "20140827_213540297", "CamHeight": "1.2", "Heading": "296", "Pitch": "179", "Roll": "82" },"Luminance":{"SysTime": "20140827_213540297", "YUV": "/sdcard/8월/2014/08/27/21/YUV/TEGRA7_YUV_20140827_213540297.jpg", "Latitude": "NULL", "Longitude": "NULL", "MinY": "NULL", "MaxY": "NULL", "MeanY": "172.5240625", "Uniformity": "NULL" }}