{"Camera":{"SysTime": "20140827_222238720", "Parameter": {"focus_mode" : "continuous-video", "width":"1280", "height": "720"}, "File": "/sdcard/8월/2014/08/27/22/RGB/TEGRA7_RGB_20140827_222238720.jpg" },"Tracking":{"SysTime": "20140827_222238720", "X": "564", "Y": "404", "W": "160", "H": "60", "File": "/sdcard/8월/2014/08/27/22/TRACKING/TEGRA7_TRACKING_20140827_222238720.jpg" },"GPS":{"UtcTime": "1409145755000", "Latitude": "37.66407398041338", "Longitude": "126.70846866443753", "Speed": "22.501715", "Altitude": "55.0", "Accuracy": "5.7004385" },"Attitude":{"SysTime": "20140827_222238720", "CamHeight": "1.2", "Heading": "40", "Pitch": "179", "Roll": "89" },"Luminance":{"SysTime": "20140827_222238720", "YUV": "/sdcard/8월/2014/08/27/22/YUV/TEGRA7_YUV_20140827_222238720.jpg", "Latitude": "NULL", "Longitude": "NULL", "MinY": "NULL", "MaxY": "NULL", "MeanY": "110.51239583333333", "Uniformity": "NULL" }}